compose_steroids/__init__.py
compose_steroids/__main__.py
compose_steroids/exceptions.py
compose_steroids/steroids.py
compose_steroids/yaml.py
compose_steroids/modules/__init__.py
compose_steroids/modules/base.py
compose_steroids/modules/loadbalancer.py
compose_steroids/modules/secrets.py
compose_steroids/modules/services.py
compose_steroids/modules/volumes.py
compose_steroids-0.1.1.dist-info/DESCRIPTION.rst
compose_steroids-0.1.1.dist-info/LICENSE.txt
compose_steroids-0.1.1.dist-info/METADATA
compose_steroids-0.1.1.dist-info/RECORD
compose_steroids-0.1.1.dist-info/WHEEL
compose_steroids-0.1.1.dist-info/entry_points.txt
compose_steroids-0.1.1.dist-info/metadata.json
compose_steroids-0.1.1.dist-info/top_level.txt
