Metadata-Version: 2.0
Name: compose-steroids
Version: 0.1.1
Summary: Adding missing features to Docker Compose files
Home-page: https://bitbucket.org/merixstudio/compose-steroids
Author: MERIXSTUDIO
Author-email: code@merixstudio.com
License: MIT
Platform: UNKNOWN
Classifier: License :: OSI Approved :: MIT License
Classifier: Operating System :: OS Independent
Classifier: Programming Language :: Python :: 3
Classifier: Programming Language :: Python :: 3.5
Classifier: Programming Language :: Python :: 3.6
Requires-Dist: pyyaml
